sorrel/__init__.py
sorrel/action/action_spec.py
sorrel/agents/__init__.py
sorrel/agents/agent.py
sorrel/buffers.py
sorrel/entities/__init__.py
sorrel/entities/basic_entities.py
sorrel/entities/entity.py
sorrel/environment.py
sorrel/examples/README.md
sorrel/examples/__init__.py
sorrel/examples/cleanup/agents.py
sorrel/examples/cleanup/assets/apple.png
sorrel/examples/cleanup/assets/apple_grass.png
sorrel/examples/cleanup/assets/beam.png
sorrel/examples/cleanup/assets/empty.png
sorrel/examples/cleanup/assets/grass.png
sorrel/examples/cleanup/assets/hero-back.png
sorrel/examples/cleanup/assets/hero-left.png
sorrel/examples/cleanup/assets/hero-right.png
sorrel/examples/cleanup/assets/hero.png
sorrel/examples/cleanup/assets/pollution.png
sorrel/examples/cleanup/assets/sand.png
sorrel/examples/cleanup/assets/wall.png
sorrel/examples/cleanup/assets/water.png
sorrel/examples/cleanup/assets/zap.png
sorrel/examples/cleanup/configs/config.yaml
sorrel/examples/cleanup/entities.py
sorrel/examples/cleanup/env.py
sorrel/examples/cleanup/main.py
sorrel/examples/cleanup/notebooks/human_player_test.ipynb
sorrel/examples/cleanup/world.py
sorrel/examples/treasurehunt/agents.py
sorrel/examples/treasurehunt/assets/empty.png
sorrel/examples/treasurehunt/assets/gem.png
sorrel/examples/treasurehunt/assets/hero.png
sorrel/examples/treasurehunt/assets/sand.png
sorrel/examples/treasurehunt/assets/wall.png
sorrel/examples/treasurehunt/entities.py
sorrel/examples/treasurehunt/env.py
sorrel/examples/treasurehunt/main.py
sorrel/examples/treasurehunt/world.py
sorrel/location.py
sorrel/models/__init__.py
sorrel/models/base_model.py
sorrel/models/human_player.py
sorrel/models/pytorch/__init__.py
sorrel/models/pytorch/iqn.py
sorrel/models/pytorch/layers.py
sorrel/models/pytorch/ppo.py
sorrel/models/pytorch/pytorch_base.py
sorrel/observation/embedding.py
sorrel/observation/observation_spec.py
sorrel/observation/visual_field.py
sorrel/utils/helpers.py
sorrel/utils/logging.py
sorrel-1.3.1.dist-info/LICENSE
sorrel-1.3.1.dist-info/METADATA
sorrel-1.3.1.dist-info/WHEEL
sorrel-1.3.1.dist-info/RECORD
