Metadata-Version: 2.3
Name: sorrel
Version: 1.3.1
Summary: A flexible framework for developing reinforcement learning algorithms.
License: MIT
Maintainer: Yibing Ju
Maintainer-email: bing.ju@mail.utoronto.ca
Requires-Python: >=3.12.0,<4.0.0
Classifier: License :: OSI Approved :: MIT License
Classifier: Programming Language :: Python :: 3
Classifier: Programming Language :: Python :: 3.12
Classifier: Programming Language :: Python :: 3.13
Requires-Dist: dill (>=0.3.9,<0.4.0)
Requires-Dist: flax (>=0.10.1,<0.11.0)
Requires-Dist: hydra-core (>=1.3.0,<2.0.0)
Requires-Dist: ipython (>=8.29.0,<9.0.0)
Requires-Dist: jax (>=0.4.35,<0.5.0)
Requires-Dist: matplotlib (>=3.6.1,<4.0.0)
Requires-Dist: numpy (>=1.26.4,<2.0.0)
Requires-Dist: pillow (>=11.0.0,<12.0.0)
Requires-Dist: pytest (>=8.3.5,<9.0.0)
Requires-Dist: pyyaml (>=6.0.2,<7.0.0)
Requires-Dist: tensorboard (>=2.18.0,<3.0.0)
Requires-Dist: torch (>=2.7.0,<3.0.0)
Project-URL: Documentation, https://sorrel.readthedocs.io
Project-URL: Homepage, https://github.com/social-ai-uoft/sorrel
Project-URL: Paper, https://doi.org/10.48550/arXiv.2506.00228
